cmsplugin_demo
