Metadata-Version: 1.1
Name: cmsplugin-demo
Version: 1.0.8
Summary: Extendable demo form plugin for Django CMS with spam protection and i18n
Home-page: http://github.com/vinitkumar/cmsplugin-demo
Author: Vinit Kumar
Author-email: vinit.kumar@changer.nl
License: UNKNOWN
Keywords: demo form django cms django-cms spam protection email
Platform: UNKNOWN
Classifier: Development Status :: 5 - Production/Stable
Classifier: Environment :: Web Environment
Classifier: Intended Audience :: Developers
Classifier: License :: OSI Approved :: BSD License
Classifier: Operating System :: OS Independent
Classifier: Programming Language :: Python
Classifier: Framework :: Django
